yacli_menu/__init__.py
yacli_menu/yacli_menu.py
yacli_menu-0.0.1.dist-info/LICENSE
yacli_menu-0.0.1.dist-info/METADATA
yacli_menu-0.0.1.dist-info/WHEEL
yacli_menu-0.0.1.dist-info/top_level.txt
yacli_menu-0.0.1.dist-info/RECORD
