Metadata-Version: 2.2
Name: yacli_menu
Version: 0.0.1
Summary: Yet another library for creating interactive CLI menus in Python
Author-email: afonsocrg <afonso.crg@gmail.com>
License:                                  Apache License
Project-URL: Repository, https://github.com/afonsocrg/yacli_menu
Classifier: Development Status :: 4 - Beta
Classifier: Intended Audience :: Developers
Classifier: License :: OSI Approved :: Apache Software License
Classifier: Operating System :: OS Independent
Classifier: Programming Language :: Python :: 3
Classifier: Programming Language :: Python :: 3.6
Classifier: Programming Language :: Python :: 3.7
Classifier: Programming Language :: Python :: 3.8
Classifier: Programming Language :: Python :: 3.9
Requires-Python: >=3.6
License-File: LICENSE
